{
    "Karel": {
        "heslo": "$2a$10$FETaNRgiH1Y.QYXeK02ImeAHWuV50YiSu6GorDTEJZz/e9ib5iOXG",
        "email": "capousek@spstrutnov.cz",
        "score": 3
    },
    "Honza": {
        "heslo": "$2a$10$FETaNRgiH1Y.QYXeK02ImeAHWuV50YiSu6GorDTEJZz/e9ib5iOXG",
        "score": 11,
        "oblibeneHlasky": [
            "'To je jako kdyby jsi si chtěl koupit jednu tyčinku buena, ale stejně musíš koupit blaení, ve kterém jsou 2.'",
            "'Chceš čůrat? A máš povolení od rodičů, že můžeš chodit o hodině?'"
        ]
    },
    "senkyr": {
        "heslo": "$2a$10$Jw6vKaiB3NrLJ7tdkKsTaObVcoJIBGvqfMJrkeYj5zyVlLIWRT7my",
        "score": 6,
        "oblibeneHlasky": [
            "'Dnes je 12.11 2022 a chleba...'",
            "'Přijít později než já!? No to je vrchol hulvátství…'",
            "'Pusťíme sem zimu!'",
            "'Nedělal jsi nic? Tak to musíme náležitě oznámkovat.'"
        ]
    },
    "Idk": {
        "heslo": "$2a$10$wdzwkvDANG1v2CjyDxvkPOanJ9tgZ4xGIWV1FHHCnFcLxi756VuFO",
        "score": 4
    },
    "idk": {
        "heslo": "$2a$10$wdzwkvDANG1v2CjyDxvkPOanJ9tgZ4xGIWV1FHHCnFcLxi756VuFO",
        "email": "furlong@spstrutnov.cz",
        "score": 1
    },
    "Pepa": {
        "heslo": "$2a$10$AbQaHKGDpHDV6K7Nif2eUulvcYtCHEG.6wSj.iNUoOfU0GM88VQ5a",
        "email": "pepa@spstrutnov.cz"
    },
    "pepa": {
        "heslo": "$2a$10$rNHl.xVt3W4x6fTnk8B4JupNLda9PpBhdokoJmpYaac8umEhzG/4S",
        "email": "idk@spstrutnov.cz"
    },
    "pepanaro": {
        "heslo": "$2a$10$V6KBKY9MHyl9asu.3m1ebOZbMNwtEqbMmugEO44PaWKCB6.o8M.CC",
        "email": "idk@spstrutnov.cz"
    },
    "pepakarel": {
        "heslo": "$2a$10$nVgk9gWIPQl4DXdVazek8uTtWbuPxCTgFCI4spt7w1jDM/NlABy5G",
        "email": "idk@spstrutnov.cz"
    },
    "petrfakt": {
        "heslo": "$2a$10$KRKsG8BYavDn4qT1RctVnuKJP9hs9RBvStiSaE1JbjSrh3plufAIm",
        "email": "idk@spstrutnov.cz"
    }
}